odoo/addons/helpdesk_mgmt_timesheet_time_control/README.rst
odoo/addons/helpdesk_mgmt_timesheet_time_control/__init__.py
odoo/addons/helpdesk_mgmt_timesheet_time_control/__manifest__.py
odoo/addons/helpdesk_mgmt_timesheet_time_control/i18n/es.po
odoo/addons/helpdesk_mgmt_timesheet_time_control/i18n/es_AR.po
odoo/addons/helpdesk_mgmt_timesheet_time_control/i18n/helpdesk_mgmt_timesheet_time_control.pot
odoo/addons/helpdesk_mgmt_timesheet_time_control/i18n/hu.po
odoo/addons/helpdesk_mgmt_timesheet_time_control/models/__init__.py
odoo/addons/helpdesk_mgmt_timesheet_time_control/models/helpdesk_ticket.py
odoo/addons/helpdesk_mgmt_timesheet_time_control/readme/CONTRIBUTORS.rst
odoo/addons/helpdesk_mgmt_timesheet_time_control/readme/DESCRIPTION.rst
odoo/addons/helpdesk_mgmt_timesheet_time_control/readme/INSTALL.rst
odoo/addons/helpdesk_mgmt_timesheet_time_control/readme/USAGE.rst
odoo/addons/helpdesk_mgmt_timesheet_time_control/static/description/icon.png
odoo/addons/helpdesk_mgmt_timesheet_time_control/static/description/index.html
odoo/addons/helpdesk_mgmt_timesheet_time_control/tests/__init__.py
odoo/addons/helpdesk_mgmt_timesheet_time_control/tests/test_helpdesk_timesheet_time_control.py
odoo/addons/helpdesk_mgmt_timesheet_time_control/views/helpdesk_ticket.xml
odoo/addons/helpdesk_mgmt_timesheet_time_control/wizards/__init__.py
odoo/addons/helpdesk_mgmt_timesheet_time_control/wizards/hr_timesheet_switch.py
odoo13_addon_helpdesk_mgmt_timesheet_time_control-13.0.1.1.0.dist-info/METADATA
odoo13_addon_helpdesk_mgmt_timesheet_time_control-13.0.1.1.0.dist-info/WHEEL
odoo13_addon_helpdesk_mgmt_timesheet_time_control-13.0.1.1.0.dist-info/top_level.txt
odoo13_addon_helpdesk_mgmt_timesheet_time_control-13.0.1.1.0.dist-info/RECORD
