Metadata-Version: 2.1
Name: odoo13-addon-helpdesk-mgmt-timesheet-time-control
Version: 13.0.1.1.0
Summary: Helpdesk Management Timesheet Time Control
Home-page: https://o4sb.com
Author: Graeme Gellatly,Odoo Community Association (OCA)
Author-email: support@odoo-community.org
License: AGPL-3
Platform: UNKNOWN
Classifier: Programming Language :: Python
Classifier: Framework :: Odoo
Classifier: Framework :: Odoo :: 13.0
Classifier: License :: OSI Approved :: GNU Affero General Public License v3
Requires-Python: >=3.5
Requires-Dist: odoo13-addon-helpdesk-mgmt-project
Requires-Dist: odoo13-addon-helpdesk-mgmt-timesheet
Requires-Dist: odoo13-addon-project-timesheet-time-control
Requires-Dist: odoo (<13.1dev,>=13.0a)
